lean_repl_py/__init__.py
lean_repl_py/async_handler.py
lean_repl_py/handler.py
repl/.git
repl/.github/workflows/ci.yml
repl/.gitignore
repl/.vscode/copyright.code-snippets
repl/.vscode/extensions.json
repl/.vscode/module-docstring.code-snippets
repl/.vscode/settings.json
repl/README.md
repl/REPL/Frontend.lean
repl/REPL/JSON.lean
repl/REPL/Lean/ContextInfo.lean
repl/REPL/Lean/Environment.lean
repl/REPL/Lean/InfoTree/ToJson.lean
repl/REPL/Lean/InfoTree.lean
repl/REPL/Main.lean
repl/REPL/Snapshots.lean
repl/REPL/Util/Path.lean
repl/REPL/Util/Pickle.lean
repl/REPL.lean
repl/lake-manifest.json
repl/lakefile.toml
repl/lean-toolchain
repl/test/Mathlib/.gitignore
repl/test/Mathlib/H20231110.sh
repl/test/Mathlib/ReplMathlibTests.lean
repl/test/Mathlib/lake-manifest.json
repl/test/Mathlib/lakefile.toml
repl/test/Mathlib/lean-toolchain
repl/test/Mathlib/test/20240209.expected.out
repl/test/Mathlib/test/20240209.in
repl/test/Mathlib/test/20240209.lean
repl/test/Mathlib/test/H20231020.expected.out
repl/test/Mathlib/test/H20231020.in
repl/test/Mathlib/test/H20231020.lean
repl/test/Mathlib/test/H20231110.expected.out
repl/test/Mathlib/test/H20231110.in
repl/test/Mathlib/test/H20231115.expected.out
repl/test/Mathlib/test/H20231115.in
repl/test/Mathlib/test/H20231115_2.expected.out
repl/test/Mathlib/test/H20231115_2.in
repl/test/Mathlib/test/H20231115_3.expected.out
repl/test/Mathlib/test/H20231115_3.in
repl/test/Mathlib/test/H20231214.in
repl/test/Mathlib/test/H20231214.lean
repl/test/Mathlib/test/H20231215.expected.out
repl/test/Mathlib/test/H20231215.in
repl/test/Mathlib/test/H20231215_2.expected.out
repl/test/Mathlib/test/H20231215_2.in
repl/test/Mathlib/test/exact.expected.out
repl/test/Mathlib/test/exact.in
repl/test/Mathlib/test/import_Mathlib.lean
repl/test/Mathlib/test/induction.expected.out
repl/test/Mathlib/test/induction.in
repl/test/Mathlib/test/induction.lean
repl/test/Mathlib/test/on_goal.expected.out
repl/test/Mathlib/test/on_goal.in
lean_repl_py-0.1.13.dist-info/LICENSE
lean_repl_py-0.1.13.dist-info/METADATA
lean_repl_py-0.1.13.dist-info/WHEEL
lean_repl_py-0.1.13.dist-info/RECORD
