Metadata-Version: 2.1
Name: lean-repl-py
Version: 0.1.13
Summary: A Python application to interact with the Lean REPL.
License: MIT
Author: Simon Sorg
Author-email: simonsorg13@gmail.com
Requires-Python: >=3.9,<4.0
Classifier: License :: OSI Approved :: MIT License
Classifier: Programming Language :: Python :: 3
Classifier: Programming Language :: Python :: 3.9
Classifier: Programming Language :: Python :: 3.10
Classifier: Programming Language :: Python :: 3.11
Classifier: Programming Language :: Python :: 3.12
Classifier: Programming Language :: Python :: 3.13
Requires-Dist: pydantic (>=2.10.3,<3.0.0)
